README.rst
setup.py
coinspot/__init__.py
coinspot/coinspot.py
py_coinspot_api.egg-info/PKG-INFO
py_coinspot_api.egg-info/SOURCES.txt
py_coinspot_api.egg-info/dependency_links.txt
py_coinspot_api.egg-info/top_level.txt