Metadata-Version: 1.1
Name: py-coinspot-api
Version: 0.2.2
Summary: A python library for the Coinspot API
Home-page: https://github.com/geekpete/py-coinspot-api
Author: Peter Dyson
Author-email: pete@geekpete.com
License: GPLv3
Keywords: coinspot api development bitcoin dogecoin litecoin cryptocurrency
Platform: UNKNOWN
Classifier: Development Status :: 5 - Production/Stable
Classifier: Intended Audience :: Developers
Classifier: Topic :: Software Development :: Libraries :: Python Modules
Classifier: License :: OSI Approved :: GNU General Public License v3 (GPLv3)
Classifier: Programming Language :: Python :: 2
Classifier: Programming Language :: Python :: 2.6
Classifier: Programming Language :: Python :: 2.7
